skimage/__init__.py
skimage/_build.py
skimage/conftest.py
skimage/setup.py
skimage/_shared/__init__.py
skimage/_shared/_geometry.py
skimage/_shared/_tempfile.py
skimage/_shared/_warnings.py
skimage/_shared/fast_exp.cp36-win_amd64.pyd
skimage/_shared/fft.py
skimage/_shared/geometry.cp36-win_amd64.pyd
skimage/_shared/interpolation.cp36-win_amd64.pyd
skimage/_shared/setup.py
skimage/_shared/testing.py
skimage/_shared/transform.cp36-win_amd64.pyd
skimage/_shared/utils.py
skimage/_shared/version_requirements.py
skimage/_shared/tests/__init__.py
skimage/_shared/tests/test_fast_exp.py
skimage/_shared/tests/test_geometry.py
skimage/_shared/tests/test_interpolation.py
skimage/_shared/tests/test_safe_as_int.py
skimage/_shared/tests/test_testing.py
skimage/_shared/tests/test_utils.py
skimage/_shared/tests/test_version_requirements.py
skimage/_shared/tests/test_warnings.py
skimage/color/__init__.py
skimage/color/adapt_rgb.py
skimage/color/colorconv.py
skimage/color/colorlabel.py
skimage/color/delta_e.py
skimage/color/rgb_colors.py
skimage/color/tests/__init__.py
skimage/color/tests/test_adapt_rgb.py
skimage/color/tests/test_colorconv.py
skimage/color/tests/test_colorlabel.py
skimage/color/tests/test_delta_e.py
skimage/data/README.txt
skimage/data/__init__.py
skimage/data/_binary_blobs.py
skimage/data/_registry.py
skimage/data/astronaut.png
skimage/data/brick.png
skimage/data/camera.png
skimage/data/chelsea.png
skimage/data/chessboard_GRAY.png
skimage/data/chessboard_RGB.png
skimage/data/clock_motion.png
skimage/data/coffee.png
skimage/data/coins.png
skimage/data/color.png
skimage/data/grass.png
skimage/data/gravel.png
skimage/data/horse.png
skimage/data/hubble_deep_field.jpg
skimage/data/ihc.png
skimage/data/lbpcascade_frontalface_opencv.xml
skimage/data/lfw_subset.npy
skimage/data/logo.png
skimage/data/microaneurysms.png
skimage/data/moon.png
skimage/data/motorcycle_disp.npz
skimage/data/motorcycle_left.png
skimage/data/motorcycle_right.png
skimage/data/page.png
scikit_image_augument_img-0.0.2.dist-info/LICENSE.txt
scikit_image_augument_img-0.0.2.dist-info/METADATA
scikit_image_augument_img-0.0.2.dist-info/WHEEL
scikit_image_augument_img-0.0.2.dist-info/entry_points.txt
scikit_image_augument_img-0.0.2.dist-info/top_level.txt
scikit_image_augument_img-0.0.2.dist-info/RECORD
